openvpn_ldap_auth/__init__.py
openvpn_ldap_auth/main.py
openvpn_ldap_auth-0.1.8.dist-info/LICENSE
openvpn_ldap_auth-0.1.8.dist-info/METADATA
openvpn_ldap_auth-0.1.8.dist-info/WHEEL
openvpn_ldap_auth-0.1.8.dist-info/entry_points.txt
openvpn_ldap_auth-0.1.8.dist-info/RECORD
